{
  "id": "io.ominousness.modernxi",
  "name": "ModernXI",
  "latest": "0.1.0",
  "repository": "Packix",
  "url": "http://cydia.saurik.com/package/io.ominousness.modernxi/",
  "shortDescription": "A tweak that does something weird to notifications.",
  "category": "Tweaks",
  "author": "Ominousness",
  "commercial": false,
  "date": "2018-07-14T17:43:36Z",
  "versions": [
    {
      "tweakVersion": "0.1.0",
      "iOSVersion": "11.3.1",
      "repository": "Packix",
      "date": "2018-07-14T17:43:36Z",
      "outcome": {
        "calculatedStatus": "Working",
        "percentage": 100,
        "good": 16,
        "bad": 0,
        "total": 16,
        "arch32": {
          "total": 0,
          "good": 0,
          "bad": 0,
          "percentage": 0,
          "calculatedStatus": "Unknown"
        }
      },
      "users": [
        {
          "status": "working",
          "device": "iPhone9,1",
          "issues": "",
          "date": "2018-07-14T17:43:36Z",
          "userName": "Yazdankhazeni",
          "issueNumber": 26600,
          "arch32": false
        },
        {
          "status": "working",
          "device": "iPhone10,3",
          "issues": "",
          "date": "2018-07-14T17:41:34Z",
          "userName": "7amadz",
          "issueNumber": 26594,
          "arch32": false
        },
        {
          "status": "working",
          "device": "iPhone9,3",
          "issues": "",
          "date": "2018-07-14T17:41:28Z",
          "userName": "ItayMayo",
          "issueNumber": 26593,
          "arch32": false
        },
        {
          "status": "partial",
          "device": "iPhone10,3",
          "issues": "Banner notifications leave a shadow in the outline of the original banner making it noticeable. Still nice tho!",
          "date": "2018-07-14T17:40:34Z",
          "userName": "danteee32",
          "issueNumber": 26592,
          "arch32": false
        },
        {
          "status": "working",
          "device": "iPhone10,6",
          "issues": "",
          "date": "2018-07-14T17:34:52Z",
          "userName": "Midnite7",
          "issueNumber": 26585,
          "arch32": false
        },
        {
          "status": "working",
          "device": "iPhone9,4",
          "issues": "",
          "date": "2018-07-14T18:13:56Z",
          "userName": "AhmaadACM",
          "issueNumber": 26621,
          "arch32": false
        },
        {
          "status": "working",
          "device": "iPhone9,3",
          "issues": "",
          "date": "2018-07-14T19:16:19Z",
          "userName": "Milchkarl",
          "issueNumber": 26689,
          "arch32": false
        },
        {
          "status": "working",
          "device": "iPhone10,3",
          "issues": "",
          "date": "2018-07-14T20:33:56Z",
          "userName": "cumanzor",
          "issueNumber": 26719,
          "arch32": false
        },
        {
          "status": "working",
          "device": "iPhone6,1",
          "issues": "",
          "date": "2018-07-15T04:44:49Z",
          "userName": "sudeep-08",
          "issueNumber": 26934,
          "arch32": false
        },
        {
          "status": "working",
          "device": "iPhone10,3",
          "issues": "",
          "date": "2018-07-15T13:51:57Z",
          "userName": "RCodispoti",
          "issueNumber": 27222,
          "arch32": false
        },
        {
          "status": "working",
          "device": "iPhone9,2",
          "issues": "",
          "date": "2018-07-15T14:05:46Z",
          "userName": "sambailey54",
          "issueNumber": 27231,
          "arch32": false
        },
        {
          "status": "working",
          "device": "iPhone10,6",
          "issues": "",
          "date": "2018-07-15T14:42:44Z",
          "userName": "gena3ekiller",
          "issueNumber": 27249,
          "arch32": false
        },
        {
          "status": "working",
          "device": "iPhone10,6",
          "issues": "",
          "date": "2018-07-15T17:13:38Z",
          "userName": "vpww",
          "issueNumber": 27339,
          "arch32": false
        },
        {
          "status": "working",
          "device": "iPhone10,2",
          "issues": "",
          "date": "2018-07-16T18:20:47Z",
          "userName": "fuzzy35",
          "issueNumber": 28028,
          "arch32": false
        },
        {
          "status": "working",
          "device": "iPhone10,6",
          "issues": "",
          "date": "2018-07-16T20:04:32Z",
          "userName": "syto203",
          "issueNumber": 28103,
          "arch32": false
        },
        {
          "status": "working",
          "device": "iPhone10,6",
          "issues": "",
          "date": "2018-07-17T15:36:42Z",
          "userName": "SavouryMonkey",
          "issueNumber": 28776,
          "arch32": false
        }
      ]
    },
    {
      "tweakVersion": "0.1.0",
      "iOSVersion": "11.2.6",
      "repository": "Packix",
      "date": "2018-07-14T22:25:41Z",
      "outcome": {
        "calculatedStatus": "Working",
        "percentage": 100,
        "good": 2,
        "bad": 0,
        "total": 2,
        "arch32": {
          "total": 0,
          "good": 0,
          "bad": 0,
          "percentage": 0,
          "calculatedStatus": "Unknown"
        }
      },
      "users": [
        {
          "status": "working",
          "device": "iPhone8,1",
          "issues": "",
          "date": "2018-07-14T22:25:41Z",
          "userName": "xxHoBoZxx",
          "issueNumber": 26783,
          "arch32": false
        },
        {
          "status": "working",
          "device": "iPhone8,2",
          "issues": "",
          "date": "2018-07-15T19:57:30Z",
          "userName": "d3vCr0w",
          "issueNumber": 27404,
          "arch32": false
        }
      ]
    },
    {
      "tweakVersion": "0.1.0",
      "iOSVersion": "11.2.1",
      "repository": "Packix",
      "date": "2018-07-15T06:41:58Z",
      "outcome": {
        "calculatedStatus": "Working",
        "percentage": 100,
        "good": 1,
        "bad": 0,
        "total": 1,
        "arch32": {
          "total": 0,
          "good": 0,
          "bad": 0,
          "percentage": 0,
          "calculatedStatus": "Unknown"
        }
      },
      "users": [
        {
          "status": "partial",
          "device": "iPhone10,6",
          "issues": "If InteliX is installed it will not work.",
          "date": "2018-07-15T06:41:58Z",
          "userName": "OVisuals",
          "issueNumber": 26991,
          "arch32": false
        }
      ]
    },
    {
      "tweakVersion": "0.1.0",
      "iOSVersion": "11.1.2",
      "repository": "Packix",
      "date": "2018-07-15T07:08:54Z",
      "outcome": {
        "calculatedStatus": "Working",
        "percentage": 100,
        "good": 1,
        "bad": 0,
        "total": 1,
        "arch32": {
          "total": 0,
          "good": 0,
          "bad": 0,
          "percentage": 0,
          "calculatedStatus": "Unknown"
        }
      },
      "users": [
        {
          "status": "working",
          "device": "iPhone9,3",
          "issues": "",
          "date": "2018-07-15T07:08:54Z",
          "userName": "cydiareviews",
          "issueNumber": 27000,
          "arch32": false
        }
      ]
    },
    {
      "tweakVersion": "0.1.0",
      "iOSVersion": "11.4",
      "repository": "Packix",
      "date": "2018-07-15T21:27:48Z",
      "outcome": {
        "calculatedStatus": "Working",
        "percentage": 100,
        "good": 2,
        "bad": 0,
        "total": 2,
        "arch32": {
          "total": 0,
          "good": 0,
          "bad": 0,
          "percentage": 0,
          "calculatedStatus": "Unknown"
        }
      },
      "users": [
        {
          "status": "working",
          "device": "iPhone10,2",
          "issues": "",
          "date": "2018-07-15T21:27:48Z",
          "userName": "toogoodbruh",
          "issueNumber": 27535,
          "arch32": false
        },
        {
          "status": "working",
          "device": "iPhone10,5",
          "issues": "",
          "date": "2018-07-19T07:42:32Z",
          "userName": "Smurf001",
          "issueNumber": 29827,
          "arch32": false
        }
      ]
    },
    {
      "tweakVersion": "0.1.0",
      "iOSVersion": "11.3",
      "repository": "Packix",
      "date": "2018-07-19T07:48:25Z",
      "outcome": {
        "calculatedStatus": "Working",
        "percentage": 100,
        "good": 1,
        "bad": 0,
        "total": 1,
        "arch32": {
          "total": 0,
          "good": 0,
          "bad": 0,
          "percentage": 0,
          "calculatedStatus": "Unknown"
        }
      },
      "users": [
        {
          "status": "working",
          "device": "iPhone10,5",
          "issues": "",
          "date": "2018-07-19T07:48:25Z",
          "userName": "Shawnyboi94",
          "issueNumber": 29830,
          "arch32": false
        }
      ]
    }
  ]
}
